MANIFEST.in
setup.cfg
setup.py
webium/__init__.py
webium/base_page.py
webium/cookie.py
webium/driver.py
webium/errors.py
webium/find.py
webium/no_implicitly_wait.py
webium/settings.py
webium/wait.py
webium/windows_handler.py
webium.egg-info/PKG-INFO
webium.egg-info/SOURCES.txt
webium.egg-info/dependency_links.txt
webium.egg-info/entry_points.txt
webium.egg-info/requires.txt
webium.egg-info/top_level.txt
webium/controls/__init__.py
webium/controls/checkbox.py
webium/controls/click.py
webium/controls/image.py
webium/controls/link.py
webium/controls/select.py
webium/jquery/__init__.py
webium/jquery/jquery-1.10.2.js
webium/plugins/__init__.py
webium/plugins/browser_closer.py