Metadata-Version: 1.1
Name: webium
Version: 1.0.4
Summary: Webium is a Page Object pattern implementation library for Python (http://martinfowler.com/bliki/PageObject.html). It allows you to extend WebElement class to your custom controls like Link, Button and group them as pages.
Home-page: https://github.com/wgnet/webium
Author: Wargaming.NET
Author-email: i_khrol@wargaming.net
License: UNKNOWN
Platform: UNKNOWN
Classifier: Intended Audience :: Developers
Classifier: Operating System :: OS Independent
Classifier: Programming Language :: Python
Classifier: Programming Language :: Python :: 2.7
